ltk/__init__.py
ltk/azure/__init__.py
ltk/azure/blob_service.py
ltk/filters/__init__.py
ltk/geometry/__init__.py
ltk/geometry/pointcloud.py
ltk/io/__init__.py
ltk/io/converter.py
ltk/segmentation/__init__.py
ltk/splitter/__init__.py
ltk/splitter/splitter.py
ltk/synthetic_data/__init__.py
ltk/visualization/__init__.py
scanplan_lidar_toolkit-0.0.4.dist-info/LICENSE
scanplan_lidar_toolkit-0.0.4.dist-info/METADATA
scanplan_lidar_toolkit-0.0.4.dist-info/WHEEL
scanplan_lidar_toolkit-0.0.4.dist-info/top_level.txt
scanplan_lidar_toolkit-0.0.4.dist-info/RECORD
