Metadata-Version: 2.1
Name: scanplan-lidar-toolkit
Version: 0.0.4
Summary: ScanPlan LiDAR Tool Kit
Home-page: https://github.com/bimbuildings/ltk
Author: scan-plan.nl
Author-email: shayan@scan-plan.nl
License: Licensed to ScanPlan
Keywords: lidar gis las
Classifier: Intended Audience :: Developers
Classifier: License :: OSI Approved :: MIT License
Classifier: Operating System :: OS Independent
Classifier: Programming Language :: Python :: 3
Requires-Python: >=3.8
License-File: LICENSE
Requires-Dist: open3d
Requires-Dist: laspy[lazrs]
Requires-Dist: numpy
Requires-Dist: setuptools
Requires-Dist: azure-identity
Requires-Dist: azure-storage-blob
